gxsimcom/__init__.py
gxsimcom/gxsimcom.py
gxsimcom-0.0.7.dist-info/LICENSE
gxsimcom-0.0.7.dist-info/METADATA
gxsimcom-0.0.7.dist-info/WHEEL
gxsimcom-0.0.7.dist-info/top_level.txt
gxsimcom-0.0.7.dist-info/RECORD
